gcloudc/__init__.py
gcloudc/context_decorator.py
gcloudc/utils.py
gcloudc/commands/__init__.py
gcloudc/commands/management/__init__.py
gcloudc/commands/management/commands/__init__.py
gcloudc/commands/management/commands/runserver.py
gcloudc/commands/management/commands/shell.py
gcloudc/commands/management/commands/test.py
gcloudc/core/__init__.py
gcloudc/core/validators.py
gcloudc/db/__init__.py
gcloudc/db/backends/__init__.py
gcloudc/db/backends/common/__init__.py
gcloudc/db/backends/common/commands.py
gcloudc/db/backends/common/constraints.py
gcloudc/db/backends/common/formatting.py
gcloudc/db/backends/common/helpers.py
gcloudc/db/backends/common/indexing.py
gcloudc/db/backends/common/mixins.py
gcloudc/db/backends/common/slowlog.py
gcloudc/db/backends/common/base/__init__.py
gcloudc/db/backends/common/base/connection.py
gcloudc/db/backends/common/base/dbapi.py
gcloudc/db/backends/common/base/entity.py
gcloudc/db/backends/common/base/introspection.py
gcloudc/db/backends/common/base/query.py
gcloudc/db/backends/common/base/schema.py
gcloudc/db/backends/common/base/traits.py
gcloudc/db/backends/common/parsers/__init__.py
gcloudc/db/backends/common/parsers/base.py
gcloudc/db/backends/common/parsers/builder.py
gcloudc/db/backends/common/parsers/dnf.py
gcloudc/db/backends/common/parsers/expressions.py
gcloudc/db/backends/datastore/__init__.py
gcloudc/db/backends/datastore/base.py
gcloudc/db/backends/datastore/compiler.py
gcloudc/db/backends/firestore/__init__.py
gcloudc/db/backends/firestore/base.py
gcloudc/db/backends/firestore/compiler.py
gcloudc/db/models/__init__.py
gcloudc/db/models/fields/__init__.py
gcloudc/db/models/fields/allkeys-5.2.0.zip
gcloudc/db/models/fields/boolean.py
gcloudc/db/models/fields/charfields.py
gcloudc/db/models/fields/computed.py
gcloudc/db/models/fields/iterable.py
gcloudc/db/models/fields/json.py
gcloudc/db/models/fields/related.py
gcloudc/db/models/fields/firestore/__init__.py
gcloudc/forms/__init__.py
gcloudc/forms/fields.py
django_gcloud_connectors-1.5.0.dist-info/LICENSE
django_gcloud_connectors-1.5.0.dist-info/METADATA
django_gcloud_connectors-1.5.0.dist-info/WHEEL
django_gcloud_connectors-1.5.0.dist-info/top_level.txt
django_gcloud_connectors-1.5.0.dist-info/RECORD
