Metadata-Version: 2.1
Name: django-gcloud-connectors
Version: 1.5.0
Summary: A Django library for connecting to Google Cloud Datastore and Firestore from Python 3 runtimes.
Home-page: https://gitlab.com/potato-oss/google-cloud/django-gcloud-connectors
Author: Potato London Ltd.
Author-email: mail@p.ota.to
Keywords: Google Cloud Datastore,Google App Engine,Django
Classifier: Development Status :: 4 - Beta
Classifier: Intended Audience :: Developers
Classifier: License :: OSI Approved :: BSD License
Classifier: Operating System :: OS Independent
Classifier: Programming Language :: Python
License-File: LICENSE
Requires-Dist: django<6,>=4.2
Requires-Dist: pyyaml<6.1,>=6.0.1
Requires-Dist: google-cloud-datastore>=2.19.0
Requires-Dist: google-cloud-firestore>=2.15.0
Requires-Dist: pyuca==1.2
Provides-Extra: test
Requires-Dist: unittest-xml-reporting==3.2.0; extra == "test"
Requires-Dist: sleuth-mock==0.1; extra == "test"
